cmem_plugin_project_resources/__init__.py
cmem_plugin_project_resources/list.py
cmem_plugin_project_resources/list.svg
cmem_plugin_project_resources/upload.py
cmem_plugin_project_resources/upload.svg
cmem_plugin_project_resources-0.7.0.dist-info/METADATA
cmem_plugin_project_resources-0.7.0.dist-info/WHEEL
cmem_plugin_project_resources-0.7.0.dist-info/licenses/LICENSE
cmem_plugin_project_resources-0.7.0.dist-info/RECORD
